README.txt
setup.py
landsatbuoycalib/BuoyCalib.py
landsatbuoycalib/__init__.py
landsatbuoycalib/atmo_data.py
landsatbuoycalib/buoy_data.py
landsatbuoycalib/image_processing.py
landsatbuoycalib/landsat_data.py
landsatbuoycalib/merra_data.py
landsatbuoycalib/misc_functions.py
landsatbuoycalib/modeled_processing.py
landsatbuoycalib/narr_data.py
landsatbuoycalib/settings.py
landsatbuoycalib.egg-info/PKG-INFO
landsatbuoycalib.egg-info/SOURCES.txt
landsatbuoycalib.egg-info/dependency_links.txt
landsatbuoycalib.egg-info/not-zip-safe
landsatbuoycalib.egg-info/top_level.txt