Metadata-Version: 1.0
Name: landsatbuoycalib
Version: 0.1
Summary: Calculates and compares the radiance of a thermal LANSAT scene to the "ground truthradiance as measured by a NOAA buoy.
Home-page: https://github.com/ndileas/Landsat-Buoy-Calibration
Author: Nathan Dileas
Author-email: nid4986@rit.edu
License: MIT
Platform: UNKNOWN
